{
  "project_info": {
    "project_number": "961370331979",
    "project_id": "messenger-bafd0",
    "storage_bucket": "messenger-bafd0.appspot.com"
  },
  "client": [
    {
      "client_info": {
        "mobilesdk_app_id": "1:961370331979:android:ef58289990e498ef1926ce",
        "android_client_info": {
          "package_name": "com.example.messenger"
        }
      },
      "oauth_client": [
        {
          "client_id": "961370331979-uuukf696d9o2u5qi5k208uue4nlagmeq.apps.googleusercontent.com",
          "client_type": 3
        }
      ],
      "api_key": [
        {
          "current_key": "AIzaSyCtM-FK9SiPii741DArJst-p2aZLU3V0Ww"
        }
      ],
      "services": {
        "appinvite_service": {
          "other_platform_oauth_client": [
            {
              "client_id": "961370331979-uuukf696d9o2u5qi5k208uue4nlagmeq.apps.googleusercontent.com",
              "client_type": 3
            }
          ]
        }
      }
    }
  ],
  "configuration_version": "1"
}